/*     */ package com.haut.grm.service;
/*     */ 
/*     */ import com.haut.grm.bean.GlobalHandler;
/*     */ import com.haut.grm.model.Store;
/*     */ import com.haut.grm.model.StoreConfig;
/*     */ import com.haut.grm.model.system.CoreVersion;
/*     */ import com.haut.grm.repository.CargoRepository;
/*     */ import com.haut.grm.repository.business.StockSumRepository;
/*     */ import com.haut.grm.util.CoreResponseParseException;
/*     */ import com.haut.grm.util.MeasureWebServiceUtil;
/*     */ import com.haut.grm.util.MessageProducer;
/*     */ import com.haut.grm.util.Pair;
/*     */ import java.io.PrintStream;
/*     */ import java.util.ArrayList;
/*     */ import java.util.HashMap;
/*     */ import java.util.List;
/*     */ import java.util.Map;
/*     */ import java.util.concurrent.ExecutionException;
/*     */ import java.util.concurrent.Future;
/*     */ import java.util.concurrent.ScheduledExecutorService;
/*     */ import java.util.concurrent.TimeUnit;
/*     */ import java.util.concurrent.TimeoutException;
/*     */ import javax.jms.JMSException;
/*     */ import org.apache.http.NameValuePair;
/*     */ import org.apache.http.message.BasicNameValuePair;
/*     */ import org.springframework.beans.factory.annotation.Autowired;
/*     */ import org.springframework.scheduling.concurrent.ThreadPoolTaskScheduler;
/*     */ import org.springframework.stereotype.Service;
/*     */ 
/*     */ 
/*     */ 
/*     */ 
/*     */ 
/*     */ 
/*     */ 
/*     */ 
/*     */ 
/*     */ 
/*     */ 
/*     */ @Service
/*     */ public class MeasureTaskService
/*     */ {
/*     */   @Autowired
/*     */   private StoreService storeService;
/*     */   @Autowired
/*     */   private StockSumRepository ssRepo;
/*     */   @Autowired
/*     */   private CargoRepository cargoRepo;
/*     */   @Autowired
/*     */   private EntryService entryService;
/*     */   @Autowired
/*     */   private CommonService commonService;
/*     */   @Autowired
/*     */   private MessageProducer amqSender;
/*  55 */   private static final Map<String, MeasureThread> map = new HashMap();
/*     */   
/*     */   public synchronized void startMeasure(Store store, boolean isFull, String apiUrl, boolean isAuto) {
/*  58 */     boolean isNew = true;
/*     */     String confUrl;
/*  60 */     if (store.getConfig().getVersion().getCodeId().equals(Integer.valueOf(2))) {
/*  61 */       confUrl = this.commonService.getSystemVariableWithKey("CORE_SERVICE_URL_2.0");
/*  62 */       isNew = false;
/*     */     } else { 
/*  64 */       if (store.getConfig().getVersion().getCodeId().equals(Integer.valueOf(3))) {
/*  65 */         confUrl = this.commonService.getSystemVariableWithKey("CORE_SERVICE_URL_3.0");
/*     */       }
/*     */       else
/*  68 */         confUrl = this.commonService.getSystemVariableWithKey("CORE_SERVICE_URL_3.0");
/*     */     }
/*  70 */     MeasureThread mt = new MeasureThread(store, isFull, apiUrl, store.getConfig().getIsDemo().booleanValue(), 
/*  71 */       confUrl, Long.valueOf(this.commonService.getSystemVariableWithKey("MEASURE_STATUS_INTERVAL")), 
/*  72 */       Long.valueOf(this.commonService.getSystemVariableWithKey("MEASURE_WEIGHT_WAIT")), 
/*  73 */       isNew, isAuto);
/*  74 */     Thread t = new Thread(mt);
/*  75 */     map.put(store.getName(), mt);
/*  76 */     t.start();
/*     */   }
/*     */   
/*     */   public synchronized void stopAllThreads() {
/*  80 */     List<Store> stores = this.storeService.getAllCenterStores();
/*  81 */     for (Store store : stores) {
/*  82 */       this.storeService.storeSetMeasureOngoing(store, false);
/*  83 */       MeasureThread t = (MeasureThread)map.get(store.getName());
/*  84 */       if (t != null) {
/*  85 */         t.stopThread();
/*     */       }
/*  87 */       map.clear();
/*     */     }
/*     */   }
/*     */   
/*     */   public synchronized void stopMeasure(Store store) {
/*  92 */     MeasureThread t = (MeasureThread)map.get(store.getName());
/*  93 */     if (t != null) {
/*  94 */       t.stop();
/*  95 */       this.storeService.storeSetMeasureOngoing(store, false);
/*  96 */       map.remove(store.getName());
/*     */     }
/*     */   }
/*     */   
/*     */ 
/*     */   private class MeasureThread
/*     */     implements Runnable
/*     */   {
/*     */     private Store store;
/*     */     
/*     */     private List<NameValuePair> params;
/*     */     
/*     */     private MeasureTask measureTask;
/*     */     
/*     */     private Future<?> measureFuture;
/*     */     
/*     */     private boolean isFull;
/*     */     
/*     */     private String apiUrl;
/*     */     
/*     */     private boolean measureDebug;
/*     */     
/*     */     private boolean isNew;
/*     */     
/*     */     private Long statusInterval;
/*     */     private Long weightWait;
/*     */     private String confUrl;
/*     */     private boolean isAuto;
/*     */     
/*     */     public MeasureThread(Store store, boolean isFull, String apiUrl, boolean measureDebug, String confUrl, Long statusInterval, Long weightWait, boolean isNew, boolean isAuto)
/*     */     {
/* 127 */       this.isFull = isFull;
/* 128 */       this.store = store;
/* 129 */       this.apiUrl = apiUrl;
/* 130 */       this.measureDebug = measureDebug;
/* 131 */       this.statusInterval = statusInterval;
/* 132 */       this.isNew = isNew;
/* 133 */       this.isAuto = isAuto;
/* 134 */       this.weightWait = weightWait;
/* 135 */       this.params = new ArrayList();
/* 136 */       this.confUrl = confUrl;
/* 137 */       this.measureTask = new MeasureTask(this.store, isFull, apiUrl);
/* 138 */       this.params.add(new BasicNameValuePair("shebei", String.valueOf(store.getCodeId())));
/*     */     }
/*     */     
/*     */     public void run()
/*     */     {
/*     */       try {
/* 144 */         if (this.isNew) {
/* 145 */           if (this.isFull) {
/* 146 */             MeasureWebServiceUtil.executeStartMeasureNewFullAction(this.confUrl, this.params, Boolean.valueOf(this.measureDebug));
/*     */           } else {
/* 148 */             MeasureWebServiceUtil.executeStartMeasureNewAction(this.confUrl, this.params, Boolean.valueOf(this.measureDebug));
/*     */           }
/*     */         } else
/* 151 */           MeasureWebServiceUtil.executeStartMeasureAction(this.confUrl, this.params, Boolean.valueOf(this.measureDebug));
/* 152 */         this.store = MeasureTaskService.this.storeService.storeSetMeasureOngoing(this.store, true);
/* 153 */         MeasureTaskService.this.amqSender.generateStartMessage(this.store, this.apiUrl == null);
/* 154 */         this.measureFuture = GlobalHandler.getScheduler().submit(this.measureTask);
/*     */       } catch (InterruptedException e) {
/* 156 */         stopThread();
/*     */       }
/*     */       catch (Exception e) {
/* 159 */         e.printStackTrace();
/*     */         try {
/* 161 */           MeasureTaskService.this.amqSender.generateInterruptMessage(this.store, "监测终止:设备无法启动");
/*     */         } catch (JMSException e1) {
/* 163 */           e1.printStackTrace();
/*     */         }
/* 165 */         stopThread();
/*     */       }
/*     */     }
/*     */     
/*     */     public void stop() {
/*     */       try {
/* 171 */         stopThread();
/* 172 */         List<NameValuePair> param = new ArrayList();
/* 173 */         param.add(new BasicNameValuePair("shebei", String.valueOf(this.store.getCodeId())));
/* 174 */         MeasureWebServiceUtil.executeStopMeasureAction(this.confUrl, this.params, Boolean.valueOf(this.measureDebug));
/* 175 */         MeasureTaskService.this.amqSender.generateInterruptMessage(this.store, "监测终止:手动停止");
/*     */       } catch (Exception e) {
/* 177 */         e.printStackTrace();
/*     */       }
/*     */     }
/*     */     
/*     */     protected void stopThread() {
/* 182 */       if (this.measureFuture != null)
/* 183 */         this.measureFuture.cancel(true);
/* 184 */       if ((this.measureFuture != null) && (this.measureTask.weightFuture != null))
/* 185 */         this.measureTask.weightFuture.cancel(true);
/* 186 */       stopMeasure();
/*     */     }
/*     */     
/*     */     protected void stopMeasure() {
/* 190 */       MeasureTaskService.this.storeService.storeSetMeasureOngoing(this.store, false);
/* 191 */       MeasureTaskService.map.remove(this.store.getName());
/*     */     }
/*     */     
/*     */ 
/*     */     private class MeasureTask
/*     */       implements Runnable
/*     */     {
/*     */       private Store store;
/*     */       
/*     */       private WeightTask weightTask;
/*     */       
/*     */       private Future<?> weightFuture;
/*     */       
/*     */       private boolean isFull;
/*     */       private String apiUrl;
/* 206 */       private long failedCount = 0L;
/*     */       
/* 208 */       private long totalCount = 0L;
/*     */       
/* 210 */       private Integer result = Integer.valueOf(0);
/*     */       
/*     */       public MeasureTask(Store store, boolean isFull, String apiUrl) {
/* 213 */         this.isFull = isFull;
/* 214 */         this.store = store;
/* 215 */         this.apiUrl = apiUrl;
/* 216 */         this.weightTask = new WeightTask(this.store, isFull, apiUrl);
/*     */       }
/*     */       
/*     */       public void run() {
/* 220 */         Pair<Integer, Integer> result = new Pair(Integer.valueOf(0), Integer.valueOf(0));
/*     */         try {
/* 222 */           result = MeasureWebServiceUtil.executeStatusAction(MeasureTaskService.MeasureThread.this.confUrl, MeasureTaskService.MeasureThread.this.params, Boolean.valueOf(MeasureTaskService.MeasureThread.this.measureDebug), this.isFull);
/* 223 */           MeasureTaskService.this.amqSender.generateProgressMessage(this.store, result, this.apiUrl == null);
/*     */         }
/*     */         catch (JMSException localJMSException1) {}catch (TimeoutException|InterruptedException|ExecutionException e)
/*     */         {
/*     */           try {
/* 228 */             MeasureTaskService.this.amqSender.generateInterruptMessage(this.store, "监测终止:获取状态出现错误");
/*     */           } catch (JMSException e1) {
/* 230 */             e1.printStackTrace();
/*     */           }
/* 232 */           e.printStackTrace();
/* 233 */           MeasureTaskService.MeasureThread.this.stopThread();
/* 234 */           return;
/*     */         } catch (CoreResponseParseException e) {
/* 236 */           this.failedCount += 1L;
/* 237 */           if (this.failedCount > 100L) {
/*     */             try {
/* 239 */               MeasureTaskService.this.amqSender.generateInterruptMessage(this.store, "监测终止:获取状态失败次数过多");
/* 240 */               MeasureTaskService.MeasureThread.this.stopThread();
/*     */             } catch (JMSException e1) {
/* 242 */               e1.printStackTrace();
/*     */             }
/* 244 */             return;
/*     */           }
/*     */           try
/*     */           {
/* 248 */             refetch((Integer)result.getFirst());
/*     */           } catch (CoreResponseParseException e11) {
/* 250 */             MeasureTaskService.MeasureThread.this.stopThread();
/*     */             try {
/* 252 */               MeasureTaskService.this.amqSender.generateInterruptMessage(this.store, "监测终止:获取状态次数过多");
/*     */             } catch (JMSException e1) {
/* 254 */               e1.printStackTrace();
/*     */             }
/*     */           }
/* 257 */           return;
/*     */         }
/*     */         
/*     */ 
/* 261 */         if ((((Integer)result.getFirst()).equals(result.getSecond())) || (((Integer)result.getFirst()).intValue() > ((Integer)result.getSecond()).intValue())) {
/* 262 */           getWeight();
/*     */         }
/*     */         else {
/*     */           try {
/* 266 */             refetch((Integer)result.getFirst());
/*     */           } catch (CoreResponseParseException e) {
/* 268 */             MeasureTaskService.MeasureThread.this.stopThread();
/*     */             try {
/* 270 */               MeasureTaskService.this.amqSender.generateInterruptMessage(this.store, "监测终止:获取状态次数过多");
/*     */             } catch (JMSException e1) {
/* 272 */               e1.printStackTrace();
/*     */             }
/*     */           }
/* 275 */           return;
/*     */         }
/*     */       }
/*     */       
/*     */       private void refetch(Integer result) throws CoreResponseParseException {
/* 280 */         if (result.equals(this.result)) {
/* 281 */           this.totalCount += 1L;
/* 282 */           System.out.println("Error Status Count:" + this.totalCount);
/*     */         }
/*     */         else {
/* 285 */           this.totalCount = 0L;
/* 286 */           this.result = result;
/*     */         }
/* 288 */         if (this.totalCount > 100L) {
/* 289 */           throw new CoreResponseParseException("获取状态信息错误");
/*     */         }
/*     */         try {
/* 292 */           Thread.sleep(MeasureTaskService.MeasureThread.this.statusInterval.longValue());
/* 293 */           run();
/*     */         } catch (InterruptedException e) {
/*     */           try {
/* 296 */             MeasureTaskService.this.amqSender.generateInterruptMessage(this.store, "监测终止:线程被手动停止");
/*     */           } catch (JMSException e1) {
/* 298 */             e1.printStackTrace();
/*     */           }
/*     */         }
/*     */       }
/*     */       
/*     */       public void getWeight()
/*     */       {
/*     */         try {
/* 306 */           MeasureTaskService.this.amqSender.generateWeightMessage(this.store, this.apiUrl == null);
/*     */         } catch (JMSException e) {
/* 308 */           e.printStackTrace();
/*     */         }
/* 310 */         this.weightFuture = GlobalHandler.getScheduler().getScheduledExecutor().schedule(this.weightTask, MeasureTaskService.MeasureThread.this.weightWait.longValue(), TimeUnit.MILLISECONDS);
/*     */       }
/*     */       
/*     */       private class WeightTask
/*     */         implements Runnable
/*     */       {
/*     */         private Store store;
/*     */         private boolean isFull;
/*     */         private String apiUrl;
/*     */         
/*     */         public WeightTask(Store store, boolean isFull, String apiUrl)
/*     */         {
/* 322 */           this.store = store;
/* 323 */           this.isFull = isFull;
/* 324 */           this.apiUrl = apiUrl;
/*     */         }
/*     */         
/*     */         /* Error */
/*     */         public void run()
/*     */         {
/*     */           // Byte code:
/*     */           //   0: aload_0
/*     */           //   1: getfield 18	com/haut/grm/service/MeasureTaskService$MeasureThread$MeasureTask$WeightTask:this$2	Lcom/haut/grm/service/MeasureTaskService$MeasureThread$MeasureTask;
/*     */           //   4: invokestatic 34	com/haut/grm/service/MeasureTaskService$MeasureThread$MeasureTask:access$1	(Lcom/haut/grm/service/MeasureTaskService$MeasureThread$MeasureTask;)Lcom/haut/grm/service/MeasureTaskService$MeasureThread;
/*     */           //   7: invokestatic 40	com/haut/grm/service/MeasureTaskService$MeasureThread:access$0	(Lcom/haut/grm/service/MeasureTaskService$MeasureThread;)Ljava/lang/String;
/*     */           //   10: aload_0
/*     */           //   11: getfield 18	com/haut/grm/service/MeasureTaskService$MeasureThread$MeasureTask$WeightTask:this$2	Lcom/haut/grm/service/MeasureTaskService$MeasureThread$MeasureTask;
/*     */           //   14: invokestatic 34	com/haut/grm/service/MeasureTaskService$MeasureThread$MeasureTask:access$1	(Lcom/haut/grm/service/MeasureTaskService$MeasureThread$MeasureTask;)Lcom/haut/grm/service/MeasureTaskService$MeasureThread;
/*     */           //   17: invokestatic 46	com/haut/grm/service/MeasureTaskService$MeasureThread:access$1	(Lcom/haut/grm/service/MeasureTaskService$MeasureThread;)Ljava/util/List;
/*     */           //   20: aload_0
/*     */           //   21: getfield 18	com/haut/grm/service/MeasureTaskService$MeasureThread$MeasureTask$WeightTask:this$2	Lcom/haut/grm/service/MeasureTaskService$MeasureThread$MeasureTask;
/*     */           //   24: invokestatic 34	com/haut/grm/service/MeasureTaskService$MeasureThread$MeasureTask:access$1	(Lcom/haut/grm/service/MeasureTaskService$MeasureThread$MeasureTask;)Lcom/haut/grm/service/MeasureTaskService$MeasureThread;
/*     */           //   27: invokestatic 49	com/haut/grm/service/MeasureTaskService$MeasureThread:access$2	(Lcom/haut/grm/service/MeasureTaskService$MeasureThread;)Z
/*     */           //   30: invokestatic 53	java/lang/Boolean:valueOf	(Z)Ljava/lang/Boolean;
/*     */           //   33: aload_0
/*     */           //   34: getfield 18	com/haut/grm/service/MeasureTaskService$MeasureThread$MeasureTask$WeightTask:this$2	Lcom/haut/grm/service/MeasureTaskService$MeasureThread$MeasureTask;
/*     */           //   37: invokestatic 34	com/haut/grm/service/MeasureTaskService$MeasureThread$MeasureTask:access$1	(Lcom/haut/grm/service/MeasureTaskService$MeasureThread$MeasureTask;)Lcom/haut/grm/service/MeasureTaskService$MeasureThread;
/*     */           //   40: invokestatic 59	com/haut/grm/service/MeasureTaskService$MeasureThread:access$3	(Lcom/haut/grm/service/MeasureTaskService$MeasureThread;)Z
/*     */           //   43: invokestatic 53	java/lang/Boolean:valueOf	(Z)Ljava/lang/Boolean;
/*     */           //   46: aload_0
/*     */           //   47: getfield 25	com/haut/grm/service/MeasureTaskService$MeasureThread$MeasureTask$WeightTask:isFull	Z
/*     */           //   50: invokestatic 62	com/haut/grm/util/MeasureWebServiceUtil:executeWeightAction	(Ljava/lang/String;Ljava/util/List;Ljava/lang/Boolean;Ljava/lang/Boolean;Z)Lcom/haut/grm/model/entry/EntryMeasure;
/*     */           //   53: astore_1
/*     */           //   54: aload_1
/*     */           //   55: invokestatic 68	com/haut/grm/service/AuthUserService:getCurrentUser	()Lcom/haut/grm/model/meta/User;
/*     */           //   58: invokevirtual 74	com/haut/grm/model/entry/EntryMeasure:setInitiator	(Lcom/haut/grm/model/meta/User;)V
/*     */           //   61: aload_1
/*     */           //   62: aload_0
/*     */           //   63: getfield 18	com/haut/grm/service/MeasureTaskService$MeasureThread$MeasureTask$WeightTask:this$2	Lcom/haut/grm/service/MeasureTaskService$MeasureThread$MeasureTask;
/*     */           //   66: invokestatic 34	com/haut/grm/service/MeasureTaskService$MeasureThread$MeasureTask:access$1	(Lcom/haut/grm/service/MeasureTaskService$MeasureThread$MeasureTask;)Lcom/haut/grm/service/MeasureTaskService$MeasureThread;
/*     */           //   69: invokestatic 40	com/haut/grm/service/MeasureTaskService$MeasureThread:access$0	(Lcom/haut/grm/service/MeasureTaskService$MeasureThread;)Ljava/lang/String;
/*     */           //   72: aload_0
/*     */           //   73: getfield 18	com/haut/grm/service/MeasureTaskService$MeasureThread$MeasureTask$WeightTask:this$2	Lcom/haut/grm/service/MeasureTaskService$MeasureThread$MeasureTask;
/*     */           //   76: invokestatic 34	com/haut/grm/service/MeasureTaskService$MeasureThread$MeasureTask:access$1	(Lcom/haut/grm/service/MeasureTaskService$MeasureThread$MeasureTask;)Lcom/haut/grm/service/MeasureTaskService$MeasureThread;
/*     */           //   79: invokestatic 46	com/haut/grm/service/MeasureTaskService$MeasureThread:access$1	(Lcom/haut/grm/service/MeasureTaskService$MeasureThread;)Ljava/util/List;
/*     */           //   82: aload_0
/*     */           //   83: getfield 18	com/haut/grm/service/MeasureTaskService$MeasureThread$MeasureTask$WeightTask:this$2	Lcom/haut/grm/service/MeasureTaskService$MeasureThread$MeasureTask;
/*     */           //   86: invokestatic 34	com/haut/grm/service/MeasureTaskService$MeasureThread$MeasureTask:access$1	(Lcom/haut/grm/service/MeasureTaskService$MeasureThread$MeasureTask;)Lcom/haut/grm/service/MeasureTaskService$MeasureThread;
/*     */           //   89: invokestatic 49	com/haut/grm/service/MeasureTaskService$MeasureThread:access$2	(Lcom/haut/grm/service/MeasureTaskService$MeasureThread;)Z
/*     */           //   92: invokestatic 53	java/lang/Boolean:valueOf	(Z)Ljava/lang/Boolean;
/*     */           //   95: aload_0
/*     */           //   96: getfield 25	com/haut/grm/service/MeasureTaskService$MeasureThread$MeasureTask$WeightTask:isFull	Z
/*     */           //   99: invokestatic 80	com/haut/grm/util/MeasureWebServiceUtil:executeDataAction	(Ljava/lang/String;Ljava/util/List;Ljava/lang/Boolean;Z)Ljava/lang/String;
/*     */           //   102: invokevirtual 84	com/haut/grm/model/entry/EntryMeasure:setData	(Ljava/lang/String;)V
/*     */           //   105: aload_1
/*     */           //   106: aload_0
/*     */           //   107: getfield 23	com/haut/grm/service/MeasureTaskService$MeasureThread$MeasureTask$WeightTask:store	Lcom/haut/grm/model/Store;
/*     */           //   110: invokevirtual 88	com/haut/grm/model/entry/EntryMeasure:setStore	(Lcom/haut/grm/model/Store;)V
/*     */           //   113: aload_1
/*     */           //   114: aload_0
/*     */           //   115: getfield 18	com/haut/grm/service/MeasureTaskService$MeasureThread$MeasureTask$WeightTask:this$2	Lcom/haut/grm/service/MeasureTaskService$MeasureThread$MeasureTask;
/*     */           //   118: invokestatic 34	com/haut/grm/service/MeasureTaskService$MeasureThread$MeasureTask:access$1	(Lcom/haut/grm/service/MeasureTaskService$MeasureThread$MeasureTask;)Lcom/haut/grm/service/MeasureTaskService$MeasureThread;
/*     */           //   121: invokestatic 92	com/haut/grm/service/MeasureTaskService$MeasureThread:access$4	(Lcom/haut/grm/service/MeasureTaskService$MeasureThread;)Z
/*     */           //   124: invokestatic 53	java/lang/Boolean:valueOf	(Z)Ljava/lang/Boolean;
/*     */           //   127: invokevirtual 95	com/haut/grm/model/entry/EntryMeasure:setIsAuto	(Ljava/lang/Boolean;)V
/*     */           //   130: aload_1
/*     */           //   131: aload_0
/*     */           //   132: getfield 23	com/haut/grm/service/MeasureTaskService$MeasureThread$MeasureTask$WeightTask:store	Lcom/haut/grm/model/Store;
/*     */           //   135: invokevirtual 99	com/haut/grm/model/Store:getConfig	()Lcom/haut/grm/model/StoreConfig;
/*     */           //   138: invokevirtual 105	com/haut/grm/model/StoreConfig:getIsDemo	()Ljava/lang/Boolean;
/*     */           //   141: invokevirtual 111	java/lang/Boolean:booleanValue	()Z
/*     */           //   144: ifeq +7 -> 151
/*     */           //   147: iconst_0
/*     */           //   148: goto +4 -> 152
/*     */           //   151: iconst_1
/*     */           //   152: invokestatic 53	java/lang/Boolean:valueOf	(Z)Ljava/lang/Boolean;
/*     */           //   155: invokevirtual 115	com/haut/grm/model/entry/EntryMeasure:setHasData	(Ljava/lang/Boolean;)V
/*     */           //   158: aload_1
/*     */           //   159: new 118	java/util/Date
/*     */           //   162: dup
/*     */           //   163: invokespecial 120	java/util/Date:<init>	()V
/*     */           //   166: invokevirtual 121	com/haut/grm/model/entry/EntryMeasure:setTime	(Ljava/util/Date;)V
/*     */           //   169: aload_0
/*     */           //   170: getfield 18	com/haut/grm/service/MeasureTaskService$MeasureThread$MeasureTask$WeightTask:this$2	Lcom/haut/grm/service/MeasureTaskService$MeasureThread$MeasureTask;
/*     */           //   173: invokestatic 34	com/haut/grm/service/MeasureTaskService$MeasureThread$MeasureTask:access$1	(Lcom/haut/grm/service/MeasureTaskService$MeasureThread$MeasureTask;)Lcom/haut/grm/service/MeasureTaskService$MeasureThread;
/*     */           //   176: invokestatic 125	com/haut/grm/service/MeasureTaskService$MeasureThread:access$7	(Lcom/haut/grm/service/MeasureTaskService$MeasureThread;)Lcom/haut/grm/service/MeasureTaskService;
/*     */           //   179: invokestatic 129	com/haut/grm/service/MeasureTaskService:access$1	(Lcom/haut/grm/service/MeasureTaskService;)Lcom/haut/grm/repository/CargoRepository;
/*     */           //   182: getstatic 134	com/haut/grm/model/QCargo:cargo	Lcom/haut/grm/model/QCargo;
/*     */           //   185: getfield 140	com/haut/grm/model/QCargo:compartment	Lcom/haut/grm/model/QCompartment;
/*     */           //   188: getfield 144	com/haut/grm/model/QCompartment:store	Lcom/haut/grm/model/QStore;
/*     */           //   191: getfield 149	com/haut/grm/model/QStore:id	Lcom/querydsl/core/types/dsl/NumberPath;
/*     */           //   194: aload_0
/*     */           //   195: getfield 23	com/haut/grm/service/MeasureTaskService$MeasureThread$MeasureTask$WeightTask:store	Lcom/haut/grm/model/Store;
/*     */           //   198: getfield 155	com/haut/grm/model/Store:id	Ljava/io/Serializable;
/*     */           //   201: checkcast 158	java/lang/Long
/*     */           //   204: invokevirtual 160	com/querydsl/core/types/dsl/NumberPath:eq	(Ljava/lang/Object;)Lcom/querydsl/core/types/dsl/BooleanExpression;
/*     */           //   207: iconst_1
/*     */           //   208: anewarray 166	com/querydsl/core/types/OrderSpecifier
/*     */           //   211: dup
/*     */           //   212: iconst_0
/*     */           //   213: getstatic 134	com/haut/grm/model/QCargo:cargo	Lcom/haut/grm/model/QCargo;
/*     */           //   216: getfield 168	com/haut/grm/model/QCargo:activeDate	Lcom/querydsl/core/types/dsl/DatePath;
/*     */           //   219: invokevirtual 172	com/querydsl/core/types/dsl/DatePath:desc	()Lcom/querydsl/core/types/OrderSpecifier;
/*     */           //   222: aastore
/*     */           //   223: invokeinterface 178 3 0
/*     */           //   228: invokeinterface 184 1 0
/*     */           //   233: astore_2
/*     */           //   234: lconst_0
/*     */           //   235: invokestatic 190	java/lang/Long:valueOf	(J)Ljava/lang/Long;
/*     */           //   238: astore_3
/*     */           //   239: aload_1
/*     */           //   240: invokevirtual 193	com/haut/grm/model/entry/EntryMeasure:getVolume	()Ljava/lang/Double;
/*     */           //   243: invokevirtual 197	java/lang/Double:longValue	()J
/*     */           //   246: invokestatic 190	java/lang/Long:valueOf	(J)Ljava/lang/Long;
/*     */           //   249: astore 4
/*     */           //   251: goto +131 -> 382
/*     */           //   254: aload_2
/*     */           //   255: invokeinterface 203 1 0
/*     */           //   260: checkcast 209	com/haut/grm/model/Cargo
/*     */           //   263: astore 5
/*     */           //   265: aload_0
/*     */           //   266: getfield 18	com/haut/grm/service/MeasureTaskService$MeasureThread$MeasureTask$WeightTask:this$2	Lcom/haut/grm/service/MeasureTaskService$MeasureThread$MeasureTask;
/*     */           //   269: invokestatic 34	com/haut/grm/service/MeasureTaskService$MeasureThread$MeasureTask:access$1	(Lcom/haut/grm/service/MeasureTaskService$MeasureThread$MeasureTask;)Lcom/haut/grm/service/MeasureTaskService$MeasureThread;
/*     */           //   272: invokestatic 125	com/haut/grm/service/MeasureTaskService$MeasureThread:access$7	(Lcom/haut/grm/service/MeasureTaskService$MeasureThread;)Lcom/haut/grm/service/MeasureTaskService;
/*     */           //   275: invokestatic 211	com/haut/grm/service/MeasureTaskService:access$2	(Lcom/haut/grm/service/MeasureTaskService;)Lcom/haut/grm/repository/business/StockSumRepository;
/*     */           //   278: aload 5
/*     */           //   280: invokevirtual 214	com/haut/grm/model/Cargo:getId	()Ljava/io/Serializable;
/*     */           //   283: checkcast 158	java/lang/Long
/*     */           //   286: invokeinterface 218 2 0
/*     */           //   291: astore 6
/*     */           //   293: aload 6
/*     */           //   295: ifnull +87 -> 382
/*     */           //   298: aload 6
/*     */           //   300: invokevirtual 224	com/haut/grm/model/business/StockSum:getAmount	()Ljava/lang/Long;
/*     */           //   303: invokevirtual 230	java/lang/Long:longValue	()J
/*     */           //   306: aload 6
/*     */           //   308: invokevirtual 231	com/haut/grm/model/business/StockSum:getInAmount	()Ljava/lang/Long;
/*     */           //   311: invokevirtual 230	java/lang/Long:longValue	()J
/*     */           //   314: ladd
/*     */           //   315: aload 6
/*     */           //   317: invokevirtual 234	com/haut/grm/model/business/StockSum:getOutAmount	()Ljava/lang/Long;
/*     */           //   320: invokevirtual 230	java/lang/Long:longValue	()J
/*     */           //   323: lsub
/*     */           //   324: aload_3
/*     */           //   325: invokevirtual 230	java/lang/Long:longValue	()J
/*     */           //   328: ladd
/*     */           //   329: invokestatic 190	java/lang/Long:valueOf	(J)Ljava/lang/Long;
/*     */           //   332: astore_3
/*     */           //   333: aload_1
/*     */           //   334: invokevirtual 193	com/haut/grm/model/entry/EntryMeasure:getVolume	()Ljava/lang/Double;
/*     */           //   337: invokevirtual 237	java/lang/Double:doubleValue	()D
/*     */           //   340: aload 6
/*     */           //   342: invokevirtual 241	com/haut/grm/model/business/StockSum:getDeductVolume	()Ljava/lang/Double;
/*     */           //   345: invokevirtual 237	java/lang/Double:doubleValue	()D
/*     */           //   348: dsub
/*     */           //   349: aload 6
/*     */           //   351: invokevirtual 244	com/haut/grm/model/business/StockSum:getUnitWeight	()Ljava/lang/Double;
/*     */           //   354: invokevirtual 237	java/lang/Double:doubleValue	()D
/*     */           //   357: dmul
/*     */           //   358: aload 6
/*     */           //   360: invokevirtual 247	com/haut/grm/model/business/StockSum:getFactor	()Ljava/lang/Double;
/*     */           //   363: invokevirtual 237	java/lang/Double:doubleValue	()D
/*     */           //   366: dmul
/*     */           //   367: invokestatic 250	java/lang/Double:valueOf	(D)Ljava/lang/Double;
/*     */           //   370: astore 7
/*     */           //   372: aload 7
/*     */           //   374: invokevirtual 197	java/lang/Double:longValue	()J
/*     */           //   377: invokestatic 190	java/lang/Long:valueOf	(J)Ljava/lang/Long;
/*     */           //   380: astore 4
/*     */           //   382: aload_2
/*     */           //   383: invokeinterface 253 1 0
/*     */           //   388: ifne -134 -> 254
/*     */           //   391: aload_1
/*     */           //   392: aload_3
/*     */           //   393: invokevirtual 256	com/haut/grm/model/entry/EntryMeasure:setStockAmount	(Ljava/lang/Long;)V
/*     */           //   396: aload_1
/*     */           //   397: aload 4
/*     */           //   399: invokevirtual 260	com/haut/grm/model/entry/EntryMeasure:setAmount	(Ljava/lang/Long;)V
/*     */           //   402: aload_1
/*     */           //   403: invokevirtual 263	com/haut/grm/model/entry/EntryMeasure:getIsAuto	()Ljava/lang/Boolean;
/*     */           //   406: invokevirtual 111	java/lang/Boolean:booleanValue	()Z
/*     */           //   409: ifeq +20 -> 429
/*     */           //   412: aload_0
/*     */           //   413: getfield 18	com/haut/grm/service/MeasureTaskService$MeasureThread$MeasureTask$WeightTask:this$2	Lcom/haut/grm/service/MeasureTaskService$MeasureThread$MeasureTask;
/*     */           //   416: invokestatic 34	com/haut/grm/service/MeasureTaskService$MeasureThread$MeasureTask:access$1	(Lcom/haut/grm/service/MeasureTaskService$MeasureThread$MeasureTask;)Lcom/haut/grm/service/MeasureTaskService$MeasureThread;
/*     */           //   419: invokestatic 125	com/haut/grm/service/MeasureTaskService$MeasureThread:access$7	(Lcom/haut/grm/service/MeasureTaskService$MeasureThread;)Lcom/haut/grm/service/MeasureTaskService;
/*     */           //   422: invokestatic 266	com/haut/grm/service/MeasureTaskService:access$3	(Lcom/haut/grm/service/MeasureTaskService;)Lcom/haut/grm/service/EntryService;
/*     */           //   425: aload_1
/*     */           //   426: invokevirtual 269	com/haut/grm/service/EntryService:generateMeasureDiff	(Lcom/haut/grm/model/entry/EntryMeasure;)V
/*     */           //   429: aload_0
/*     */           //   430: getfield 27	com/haut/grm/service/MeasureTaskService$MeasureThread$MeasureTask$WeightTask:apiUrl	Ljava/lang/String;
/*     */           //   433: ifnonnull +73 -> 506
/*     */           //   436: aload_0
/*     */           //   437: getfield 18	com/haut/grm/service/MeasureTaskService$MeasureThread$MeasureTask$WeightTask:this$2	Lcom/haut/grm/service/MeasureTaskService$MeasureThread$MeasureTask;
/*     */           //   440: invokestatic 34	com/haut/grm/service/MeasureTaskService$MeasureThread$MeasureTask:access$1	(Lcom/haut/grm/service/MeasureTaskService$MeasureThread$MeasureTask;)Lcom/haut/grm/service/MeasureTaskService$MeasureThread;
/*     */           //   443: invokestatic 125	com/haut/grm/service/MeasureTaskService$MeasureThread:access$7	(Lcom/haut/grm/service/MeasureTaskService$MeasureThread;)Lcom/haut/grm/service/MeasureTaskService;
/*     */           //   446: invokestatic 275	com/haut/grm/service/MeasureTaskService:access$4	(Lcom/haut/grm/service/MeasureTaskService;)Lcom/haut/grm/service/CommonService;
/*     */           //   449: new 278	java/lang/StringBuilder
/*     */           //   452: dup
/*     */           //   453: ldc_w 280
/*     */           //   456: invokespecial 282	java/lang/StringBuilder:<init>	(Ljava/lang/String;)V
/*     */           //   459: aload_0
/*     */           //   460: getfield 23	com/haut/grm/service/MeasureTaskService$MeasureThread$MeasureTask$WeightTask:store	Lcom/haut/grm/model/Store;
/*     */           //   463: invokevirtual 284	com/haut/grm/model/Store:getName	()Ljava/lang/String;
/*     */           //   466: invokevirtual 288	java/lang/StringBuilder:append	(Ljava/lang/String;)Ljava/lang/StringBuilder;
/*     */           //   469: ldc_w 292
/*     */           //   472: invokevirtual 288	java/lang/StringBuilder:append	(Ljava/lang/String;)Ljava/lang/StringBuilder;
/*     */           //   475: invokevirtual 294	java/lang/StringBuilder:toString	()Ljava/lang/String;
/*     */           //   478: invokevirtual 297	com/haut/grm/service/CommonService:createSystemLog	(Ljava/lang/String;)V
/*     */           //   481: aload_0
/*     */           //   482: getfield 18	com/haut/grm/service/MeasureTaskService$MeasureThread$MeasureTask$WeightTask:this$2	Lcom/haut/grm/service/MeasureTaskService$MeasureThread$MeasureTask;
/*     */           //   485: invokestatic 34	com/haut/grm/service/MeasureTaskService$MeasureThread$MeasureTask:access$1	(Lcom/haut/grm/service/MeasureTaskService$MeasureThread$MeasureTask;)Lcom/haut/grm/service/MeasureTaskService$MeasureThread;
/*     */           //   488: invokestatic 125	com/haut/grm/service/MeasureTaskService$MeasureThread:access$7	(Lcom/haut/grm/service/MeasureTaskService$MeasureThread;)Lcom/haut/grm/service/MeasureTaskService;
/*     */           //   491: invokestatic 266	com/haut/grm/service/MeasureTaskService:access$3	(Lcom/haut/grm/service/MeasureTaskService;)Lcom/haut/grm/service/EntryService;
/*     */           //   494: aload_1
/*     */           //   495: aload_0
/*     */           //   496: getfield 23	com/haut/grm/service/MeasureTaskService$MeasureThread$MeasureTask$WeightTask:store	Lcom/haut/grm/model/Store;
/*     */           //   499: invokevirtual 302	com/haut/grm/service/EntryService:createEntryMeasure	(Lcom/haut/grm/model/entry/EntryMeasure;Lcom/haut/grm/model/Store;)Lcom/haut/grm/model/entry/EntryMeasure;
/*     */           //   502: pop
/*     */           //   503: goto +184 -> 687
/*     */           //   506: aload_0
/*     */           //   507: getfield 18	com/haut/grm/service/MeasureTaskService$MeasureThread$MeasureTask$WeightTask:this$2	Lcom/haut/grm/service/MeasureTaskService$MeasureThread$MeasureTask;
/*     */           //   510: invokestatic 34	com/haut/grm/service/MeasureTaskService$MeasureThread$MeasureTask:access$1	(Lcom/haut/grm/service/MeasureTaskService$MeasureThread$MeasureTask;)Lcom/haut/grm/service/MeasureTaskService$MeasureThread;
/*     */           //   513: invokestatic 125	com/haut/grm/service/MeasureTaskService$MeasureThread:access$7	(Lcom/haut/grm/service/MeasureTaskService$MeasureThread;)Lcom/haut/grm/service/MeasureTaskService;
/*     */           //   516: invokestatic 275	com/haut/grm/service/MeasureTaskService:access$4	(Lcom/haut/grm/service/MeasureTaskService;)Lcom/haut/grm/service/CommonService;
/*     */           //   519: new 278	java/lang/StringBuilder
/*     */           //   522: dup
/*     */           //   523: ldc_w 280
/*     */           //   526: invokespecial 282	java/lang/StringBuilder:<init>	(Ljava/lang/String;)V
/*     */           //   529: aload_0
/*     */           //   530: getfield 23	com/haut/grm/service/MeasureTaskService$MeasureThread$MeasureTask$WeightTask:store	Lcom/haut/grm/model/Store;
/*     */           //   533: invokevirtual 284	com/haut/grm/model/Store:getName	()Ljava/lang/String;
/*     */           //   536: invokevirtual 288	java/lang/StringBuilder:append	(Ljava/lang/String;)Ljava/lang/StringBuilder;
/*     */           //   539: ldc_w 306
/*     */           //   542: invokevirtual 288	java/lang/StringBuilder:append	(Ljava/lang/String;)Ljava/lang/StringBuilder;
/*     */           //   545: invokevirtual 294	java/lang/StringBuilder:toString	()Ljava/lang/String;
/*     */           //   548: invokevirtual 297	com/haut/grm/service/CommonService:createSystemLog	(Ljava/lang/String;)V
/*     */           //   551: aload_0
/*     */           //   552: getfield 27	com/haut/grm/service/MeasureTaskService$MeasureThread$MeasureTask$WeightTask:apiUrl	Ljava/lang/String;
/*     */           //   555: aload_1
/*     */           //   556: invokestatic 308	com/haut/grm/util/MeasureWebServiceUtil:executeApiData	(Ljava/lang/String;Lcom/haut/grm/model/entry/EntryMeasure;)Ljava/lang/String;
/*     */           //   559: pop
/*     */           //   560: goto +127 -> 687
/*     */           //   563: astore_2
/*     */           //   564: aload_0
/*     */           //   565: getfield 18	com/haut/grm/service/MeasureTaskService$MeasureThread$MeasureTask$WeightTask:this$2	Lcom/haut/grm/service/MeasureTaskService$MeasureThread$MeasureTask;
/*     */           //   568: invokestatic 34	com/haut/grm/service/MeasureTaskService$MeasureThread$MeasureTask:access$1	(Lcom/haut/grm/service/MeasureTaskService$MeasureThread$MeasureTask;)Lcom/haut/grm/service/MeasureTaskService$MeasureThread;
/*     */           //   571: invokestatic 125	com/haut/grm/service/MeasureTaskService$MeasureThread:access$7	(Lcom/haut/grm/service/MeasureTaskService$MeasureThread;)Lcom/haut/grm/service/MeasureTaskService;
/*     */           //   574: invokestatic 312	com/haut/grm/service/MeasureTaskService:access$0	(Lcom/haut/grm/service/MeasureTaskService;)Lcom/haut/grm/util/MessageProducer;
/*     */           //   577: aload_0
/*     */           //   578: getfield 23	com/haut/grm/service/MeasureTaskService$MeasureThread$MeasureTask$WeightTask:store	Lcom/haut/grm/model/Store;
/*     */           //   581: ldc_w 315
/*     */           //   584: invokevirtual 317	com/haut/grm/util/MessageProducer:generateInterruptMessage	(Lcom/haut/grm/model/Store;Ljava/lang/String;)V
/*     */           //   587: goto +8 -> 595
/*     */           //   590: astore_3
/*     */           //   591: aload_3
/*     */           //   592: invokevirtual 323	javax/jms/JMSException:printStackTrace	()V
/*     */           //   595: aload_2
/*     */           //   596: invokevirtual 328	java/lang/Exception:printStackTrace	()V
/*     */           //   599: aload_0
/*     */           //   600: getfield 18	com/haut/grm/service/MeasureTaskService$MeasureThread$MeasureTask$WeightTask:this$2	Lcom/haut/grm/service/MeasureTaskService$MeasureThread$MeasureTask;
/*     */           //   603: invokestatic 34	com/haut/grm/service/MeasureTaskService$MeasureThread$MeasureTask:access$1	(Lcom/haut/grm/service/MeasureTaskService$MeasureThread$MeasureTask;)Lcom/haut/grm/service/MeasureTaskService$MeasureThread;
/*     */           //   606: invokevirtual 331	com/haut/grm/service/MeasureTaskService$MeasureThread:stopThread	()V
/*     */           //   609: aload_0
/*     */           //   610: getfield 18	com/haut/grm/service/MeasureTaskService$MeasureThread$MeasureTask$WeightTask:this$2	Lcom/haut/grm/service/MeasureTaskService$MeasureThread$MeasureTask;
/*     */           //   613: invokestatic 34	com/haut/grm/service/MeasureTaskService$MeasureThread$MeasureTask:access$1	(Lcom/haut/grm/service/MeasureTaskService$MeasureThread$MeasureTask;)Lcom/haut/grm/service/MeasureTaskService$MeasureThread;
/*     */           //   616: invokestatic 125	com/haut/grm/service/MeasureTaskService$MeasureThread:access$7	(Lcom/haut/grm/service/MeasureTaskService$MeasureThread;)Lcom/haut/grm/service/MeasureTaskService;
/*     */           //   619: invokestatic 312	com/haut/grm/service/MeasureTaskService:access$0	(Lcom/haut/grm/service/MeasureTaskService;)Lcom/haut/grm/util/MessageProducer;
/*     */           //   622: aload_0
/*     */           //   623: getfield 23	com/haut/grm/service/MeasureTaskService$MeasureThread$MeasureTask$WeightTask:store	Lcom/haut/grm/model/Store;
/*     */           //   626: invokevirtual 334	com/haut/grm/util/MessageProducer:generateStopMessage	(Lcom/haut/grm/model/Store;)V
/*     */           //   629: goto +98 -> 727
/*     */           //   632: astore 9
/*     */           //   634: aload 9
/*     */           //   636: invokevirtual 323	javax/jms/JMSException:printStackTrace	()V
/*     */           //   639: goto +88 -> 727
/*     */           //   642: astore 8
/*     */           //   644: aload_0
/*     */           //   645: getfield 18	com/haut/grm/service/MeasureTaskService$MeasureThread$MeasureTask$WeightTask:this$2	Lcom/haut/grm/service/MeasureTaskService$MeasureThread$MeasureTask;
/*     */           //   648: invokestatic 34	com/haut/grm/service/MeasureTaskService$MeasureThread$MeasureTask:access$1	(Lcom/haut/grm/service/MeasureTaskService$MeasureThread$MeasureTask;)Lcom/haut/grm/service/MeasureTaskService$MeasureThread;
/*     */           //   651: invokevirtual 331	com/haut/grm/service/MeasureTaskService$MeasureThread:stopThread	()V
/*     */           //   654: aload_0
/*     */           //   655: getfield 18	com/haut/grm/service/MeasureTaskService$MeasureThread$MeasureTask$WeightTask:this$2	Lcom/haut/grm/service/MeasureTaskService$MeasureThread$MeasureTask;
/*     */           //   658: invokestatic 34	com/haut/grm/service/MeasureTaskService$MeasureThread$MeasureTask:access$1	(Lcom/haut/grm/service/MeasureTaskService$MeasureThread$MeasureTask;)Lcom/haut/grm/service/MeasureTaskService$MeasureThread;
/*     */           //   661: invokestatic 125	com/haut/grm/service/MeasureTaskService$MeasureThread:access$7	(Lcom/haut/grm/service/MeasureTaskService$MeasureThread;)Lcom/haut/grm/service/MeasureTaskService;
/*     */           //   664: invokestatic 312	com/haut/grm/service/MeasureTaskService:access$0	(Lcom/haut/grm/service/MeasureTaskService;)Lcom/haut/grm/util/MessageProducer;
/*     */           //   667: aload_0
/*     */           //   668: getfield 23	com/haut/grm/service/MeasureTaskService$MeasureThread$MeasureTask$WeightTask:store	Lcom/haut/grm/model/Store;
/*     */           //   671: invokevirtual 334	com/haut/grm/util/MessageProducer:generateStopMessage	(Lcom/haut/grm/model/Store;)V
/*     */           //   674: goto +10 -> 684
/*     */           //   677: astore 9
/*     */           //   679: aload 9
/*     */           //   681: invokevirtual 323	javax/jms/JMSException:printStackTrace	()V
/*     */           //   684: aload 8
/*     */           //   686: athrow
/*     */           //   687: aload_0
/*     */           //   688: getfield 18	com/haut/grm/service/MeasureTaskService$MeasureThread$MeasureTask$WeightTask:this$2	Lcom/haut/grm/service/MeasureTaskService$MeasureThread$MeasureTask;
/*     */           //   691: invokestatic 34	com/haut/grm/service/MeasureTaskService$MeasureThread$MeasureTask:access$1	(Lcom/haut/grm/service/MeasureTaskService$MeasureThread$MeasureTask;)Lcom/haut/grm/service/MeasureTaskService$MeasureThread;
/*     */           //   694: invokevirtual 331	com/haut/grm/service/MeasureTaskService$MeasureThread:stopThread	()V
/*     */           //   697: aload_0
/*     */           //   698: getfield 18	com/haut/grm/service/MeasureTaskService$MeasureThread$MeasureTask$WeightTask:this$2	Lcom/haut/grm/service/MeasureTaskService$MeasureThread$MeasureTask;
/*     */           //   701: invokestatic 34	com/haut/grm/service/MeasureTaskService$MeasureThread$MeasureTask:access$1	(Lcom/haut/grm/service/MeasureTaskService$MeasureThread$MeasureTask;)Lcom/haut/grm/service/MeasureTaskService$MeasureThread;
/*     */           //   704: invokestatic 125	com/haut/grm/service/MeasureTaskService$MeasureThread:access$7	(Lcom/haut/grm/service/MeasureTaskService$MeasureThread;)Lcom/haut/grm/service/MeasureTaskService;
/*     */           //   707: invokestatic 312	com/haut/grm/service/MeasureTaskService:access$0	(Lcom/haut/grm/service/MeasureTaskService;)Lcom/haut/grm/util/MessageProducer;
/*     */           //   710: aload_0
/*     */           //   711: getfield 23	com/haut/grm/service/MeasureTaskService$MeasureThread$MeasureTask$WeightTask:store	Lcom/haut/grm/model/Store;
/*     */           //   714: invokevirtual 334	com/haut/grm/util/MessageProducer:generateStopMessage	(Lcom/haut/grm/model/Store;)V
/*     */           //   717: goto +10 -> 727
/*     */           //   720: astore 9
/*     */           //   722: aload 9
/*     */           //   724: invokevirtual 323	javax/jms/JMSException:printStackTrace	()V
/*     */           //   727: return
/*     */           // Line number table:
/*     */           //   Java source line #331	-> byte code offset #0
/*     */           //   Java source line #332	-> byte code offset #54
/*     */           //   Java source line #333	-> byte code offset #61
/*     */           //   Java source line #334	-> byte code offset #105
/*     */           //   Java source line #335	-> byte code offset #113
/*     */           //   Java source line #336	-> byte code offset #130
/*     */           //   Java source line #337	-> byte code offset #158
/*     */           //   Java source line #339	-> byte code offset #169
/*     */           //   Java source line #340	-> byte code offset #234
/*     */           //   Java source line #341	-> byte code offset #239
/*     */           //   Java source line #342	-> byte code offset #251
/*     */           //   Java source line #343	-> byte code offset #254
/*     */           //   Java source line #344	-> byte code offset #265
/*     */           //   Java source line #345	-> byte code offset #293
/*     */           //   Java source line #346	-> byte code offset #298
/*     */           //   Java source line #347	-> byte code offset #333
/*     */           //   Java source line #348	-> byte code offset #372
/*     */           //   Java source line #342	-> byte code offset #382
/*     */           //   Java source line #351	-> byte code offset #391
/*     */           //   Java source line #352	-> byte code offset #396
/*     */           //   Java source line #353	-> byte code offset #402
/*     */           //   Java source line #354	-> byte code offset #412
/*     */           //   Java source line #356	-> byte code offset #429
/*     */           //   Java source line #357	-> byte code offset #436
/*     */           //   Java source line #358	-> byte code offset #481
/*     */           //   Java source line #359	-> byte code offset #503
/*     */           //   Java source line #361	-> byte code offset #506
/*     */           //   Java source line #362	-> byte code offset #551
/*     */           //   Java source line #364	-> byte code offset #560
/*     */           //   Java source line #366	-> byte code offset #564
/*     */           //   Java source line #367	-> byte code offset #587
/*     */           //   Java source line #368	-> byte code offset #591
/*     */           //   Java source line #370	-> byte code offset #595
/*     */           //   Java source line #372	-> byte code offset #599
/*     */           //   Java source line #374	-> byte code offset #609
/*     */           //   Java source line #375	-> byte code offset #629
/*     */           //   Java source line #376	-> byte code offset #634
/*     */           //   Java source line #371	-> byte code offset #642
/*     */           //   Java source line #372	-> byte code offset #644
/*     */           //   Java source line #374	-> byte code offset #654
/*     */           //   Java source line #375	-> byte code offset #674
/*     */           //   Java source line #376	-> byte code offset #679
/*     */           //   Java source line #378	-> byte code offset #684
/*     */           //   Java source line #372	-> byte code offset #687
/*     */           //   Java source line #374	-> byte code offset #697
/*     */           //   Java source line #375	-> byte code offset #717
/*     */           //   Java source line #376	-> byte code offset #722
/*     */           //   Java source line #379	-> byte code offset #727
/*     */           // Local variable table:
/*     */           //   start	length	slot	name	signature
/*     */           //   0	728	0	this	WeightTask
/*     */           //   53	503	1	result	com.haut.grm.model.entry.EntryMeasure
/*     */           //   233	150	2	itr	java.util.Iterator<com.haut.grm.model.Cargo>
/*     */           //   563	33	2	e	Exception
/*     */           //   238	155	3	sa	Long
/*     */           //   590	2	3	e1	JMSException
/*     */           //   249	149	4	aa	Long
/*     */           //   263	16	5	c	com.haut.grm.model.Cargo
/*     */           //   291	68	6	currentStock	com.haut.grm.model.business.StockSum
/*     */           //   370	3	7	_r	Double
/*     */           //   642	43	8	localObject	Object
/*     */           //   632	3	9	e	JMSException
/*     */           //   677	3	9	e	JMSException
/*     */           //   720	3	9	e	JMSException
/*     */           // Exception table:
/*     */           //   from	to	target	type
/*     */           //   0	560	563	java/lang/Exception
/*     */           //   564	587	590	javax/jms/JMSException
/*     */           //   609	629	632	javax/jms/JMSException
/*     */           //   0	599	642	finally
/*     */           //   654	674	677	javax/jms/JMSException
/*     */           //   697	717	720	javax/jms/JMSException
/*     */         }
/*     */       }
/*     */     }
/*     */   }
/*     */ }


/* Location:              C:\Users\10231\Desktop\shundedapingtai\grm\WEB-INF\classes\!\com\haut\grm\service\MeasureTaskService.class
 * Java compiler version: 8 (52.0)
 * JD-Core Version:       0.7.1
 */